pathway2cyjs.py
pathway2cyjs-0.0.4.dist-info/LICENSE
pathway2cyjs-0.0.4.dist-info/METADATA
pathway2cyjs-0.0.4.dist-info/WHEEL
pathway2cyjs-0.0.4.dist-info/top_level.txt
pathway2cyjs-0.0.4.dist-info/RECORD
